{"type":"PR","pr":{"number":19,"head":"300c39bcc9d5367795ba5f5420e199403fcc1915"},"user":"Ania P","status":"pending_review","branch":"cms/events/196.1/index","collection":"events","commitMessage":"Update Event “196.1/index”","title":"Improve - how Kanban builds continuous improvement into your work","description":"No Description!","objects":{"entry":{"path":"content/events/196.1/index.md","sha":"fa6e58275ee2c3c2e352ab0d1e2d8361abde0060"},"files":[{"path":"content/events/196.1/IMG-20200122-WA0000.jpg","sha":"0c38cc05ccfae40b2a503d3132127de57b57e98e"}]},"timeStamp":"2020-01-27T12:55:28.531Z","version":"1"}